dict.cc.py-3.1.0.data/scripts/dict.cc.py
dictcc/__init__.py
dictcc/dictcc.py
dict.cc.py-3.1.0.dist-info/METADATA
dict.cc.py-3.1.0.dist-info/WHEEL
dict.cc.py-3.1.0.dist-info/top_level.txt
dict.cc.py-3.1.0.dist-info/RECORD
