Metadata-Version: 2.1
Name: dict.cc.py
Version: 3.1.0
Summary: Unofficial dict.cc command line interface
Home-page: https://github.com/rbaron/dict.cc.py
Author: UNKNOWN
Author-email: UNKNOWN
License: UNKNOWN
Platform: UNKNOWN
Requires-Dist: beautifulsoup4
Requires-Dist: requests
Requires-Dist: colorama
